docproc/__init__.py
docproc/bin/cli.py
docproc/doc/__init__.py
docproc/doc/analyzer.py
docproc/doc/equations.py
docproc/doc/handwriting.py
docproc/doc/regions.py
docproc/writer/__init__.py
docproc/writer/csv.py
docproc/writer/filewriter.py
docproc/writer/json.py
docproc/writer/sqlite.py
docproc-1.0.0.dist-info/METADATA
docproc-1.0.0.dist-info/WHEEL
docproc-1.0.0.dist-info/entry_points.txt
docproc-1.0.0.dist-info/licenses/LICENSE.md
docproc-1.0.0.dist-info/RECORD
