Metadata-Version: 2.4
Name: docproc
Version: 1.0.0
Summary: Opinionated and Sophisticated Document Region Analyzer.
Author-email: Rithul Kamesh <hi@rithul.dev>
License-Expression: MIT
License-File: LICENSE.md
Classifier: Development Status :: 3 - Alpha
Classifier: Intended Audience :: Developers
Classifier: Programming Language :: Python :: 3.12
Classifier: Topic :: Software Development :: Libraries :: Python Modules
Requires-Python: ==3.12.8
Requires-Dist: opencv-python>=4.11.0.86
Requires-Dist: pillow<12,>=11.1.0
Requires-Dist: pymupdf<2,>=1.23.0
Requires-Dist: pytesseract>=0.3.13
Requires-Dist: rapid-latex-ocr<0.0.10,>=0.0.9
